{
    "defaultSeverity": "error",
    "extends": [
        "tslint:recommended",
        "tslint-react"
    ],
    "jsRules": {},
    "rules": {
        "quotemark": [true, "single"],
        "arrow-parens": [true, "as-needed"],
        "no-console": false,
        "no-var-requires": false,
        "jsx-boolean-value": false,
        "interface-name": [true, "never-prefix"],
        "indent": [true, "spaces", 2],
        "object-literal-sort-keys": false,
        "no-empty-interface": false
    },
    "rulesDirectory": []
}
